archetypes.referencebrowserwidget-2.5.11-py2.7-nspkg.pth
archetypes/referencebrowserwidget/README.txt
archetypes/referencebrowserwidget/__init__.py
archetypes/referencebrowserwidget/adapter.py
archetypes/referencebrowserwidget/config.py
archetypes/referencebrowserwidget/configure.zcml
archetypes/referencebrowserwidget/demo.py
archetypes/referencebrowserwidget/interfaces.py
archetypes/referencebrowserwidget/utils.py
archetypes/referencebrowserwidget/widget.py
archetypes/referencebrowserwidget/browser/__init__.py
archetypes/referencebrowserwidget/browser/configure.zcml
archetypes/referencebrowserwidget/browser/popup.pt
archetypes/referencebrowserwidget/browser/view.py
archetypes/referencebrowserwidget/profiles/default/metadata.xml
archetypes/referencebrowserwidget/profiles/default/skins.xml
archetypes/referencebrowserwidget/profiles/sample_types/archetype_tool.xml
archetypes/referencebrowserwidget/profiles/sample_types/types.xml
archetypes/referencebrowserwidget/profiles/sample_types/types/RefBrowserDemo.xml
archetypes/referencebrowserwidget/skins/referencebrowser/referencebrowser.js
archetypes/referencebrowserwidget/skins/referencebrowser/referencebrowser.js.metadata
archetypes/referencebrowserwidget/skins/referencebrowser/referencebrowser.pt
archetypes/referencebrowserwidget/tests/__init__.py
archetypes/referencebrowserwidget/tests/base.py
archetypes/referencebrowserwidget/tests/reference_access.txt
archetypes/referencebrowserwidget/tests/reference_order.txt
archetypes/referencebrowserwidget/tests/sample.pt
archetypes/referencebrowserwidget/tests/test_browser.py
archetypes/referencebrowserwidget/tests/test_doctests.py
archetypes/referencebrowserwidget/tests/test_product.py
archetypes/referencebrowserwidget/tests/test_utils.py
archetypes.referencebrowserwidget-2.5.11.dist-info/METADATA
archetypes.referencebrowserwidget-2.5.11.dist-info/WHEEL
archetypes.referencebrowserwidget-2.5.11.dist-info/entry_points.txt
archetypes.referencebrowserwidget-2.5.11.dist-info/namespace_packages.txt
archetypes.referencebrowserwidget-2.5.11.dist-info/top_level.txt
archetypes.referencebrowserwidget-2.5.11.dist-info/RECORD
