Metadata-Version: 2.1
Name: archetypes.referencebrowserwidget
Version: 2.5.11
Summary: A referencebrowser implementation for Archetypes
Home-page: https://pypi.org/project/archetypes.referencebrowserwidget
Author: Tom Gross
Author-email: itconsense@gmail.com
License: ZPL 2.1
Keywords: Relation Widget
Platform: UNKNOWN
Classifier: Development Status :: 6 - Mature
Classifier: Framework :: Plone
Classifier: Framework :: Plone :: 4.3
Classifier: Framework :: Plone :: 5.0
Classifier: Framework :: Plone :: 5.1
Classifier: Framework :: Plone :: 5.2
Classifier: Framework :: Plone :: Core
Classifier: License :: OSI Approved :: Zope Public License
Classifier: Programming Language :: Python
Classifier: Programming Language :: Python :: 2.6
Classifier: Programming Language :: Python :: 2.7
Classifier: Topic :: Software Development :: Libraries :: Python Modules
Requires-Dist: setuptools
Requires-Dist: zope.interface
Requires-Dist: zope.component
Requires-Dist: zope.formlib
Requires-Dist: plone.app.jquerytools (>=1.1b1)
